python_luminous_mesh/__init__.py
python_luminous_mesh/auth/__pycache__/credentials.cpython-313.pyc
python_luminous_mesh/auth/credentials.py
python_luminous_mesh/config/__pycache__/settings.cpython-313.pyc
python_luminous_mesh/config/settings.py
python_luminous_mesh/core/__pycache__/client.cpython-313.pyc
python_luminous_mesh/core/client.py
python_luminous_mesh/protobuf/node_pb2.py
python_luminous_mesh/protobuf/node_pb2_grpc.py
python_luminous_mesh/utils/__pycache__/metrics.cpython-313.pyc
python_luminous_mesh/utils/metrics.py
python_luminous_mesh/utils/status.py
python_luminous_mesh-0.1.2.dist-info/METADATA
python_luminous_mesh-0.1.2.dist-info/WHEEL
python_luminous_mesh-0.1.2.dist-info/entry_points.txt
python_luminous_mesh-0.1.2.dist-info/RECORD
