Metadata-Version: 2.3
Name: python-luminous-mesh
Version: 0.1.2
Summary: A Python client for Luminous Mesh service
Author: Raphael
Author-email: camblong.raphael@epitech.eu
Requires-Python: >=3.13
Classifier: Programming Language :: Python :: 3
Classifier: Programming Language :: Python :: 3.13
Requires-Dist: cryptography (>=44.0.2,<45.0.0)
Requires-Dist: grpcio (>=1.71.0,<2.0.0)
Requires-Dist: grpcio-tools (>=1.71.0,<2.0.0)
Requires-Dist: prometheus-client (>=0.21.1,<0.22.0)
Requires-Dist: psutil (>=7.0.0,<8.0.0)
Requires-Dist: pyyaml (>=6.0.2,<7.0.0)
Requires-Dist: structlog (>=25.2.0,<26.0.0)
Requires-Dist: tenacity (>=9.1.2,<10.0.0)
